orca_hls_utils/DateRangeHLSStream.py
orca_hls_utils/HLSStream.py
orca_hls_utils/__init__.py
orca_hls_utils/_version.py
orca_hls_utils/datetime_utils.py
orca_hls_utils/s3_utils.py
orca_hls_utils/scraper.py
orca_hls_utils-0.0.4.dist-info/LICENSE
orca_hls_utils-0.0.4.dist-info/METADATA
orca_hls_utils-0.0.4.dist-info/WHEEL
orca_hls_utils-0.0.4.dist-info/top_level.txt
orca_hls_utils-0.0.4.dist-info/RECORD
