Metadata-Version: 2.1
Name: orca-hls-utils
Version: 0.0.4
Summary: Collection of utilities for getting Orcasound HLS data
Home-page: https://github.com/orcasound/orca-hls-utils
Author: Example Author
Author-email: author@example.com
Project-URL: Bug Tracker, https://github.com/orcasound/orca-hls-utils/issues
Classifier: Programming Language :: Python :: 3
Classifier: License :: OSI Approved :: MIT License
Classifier: Operating System :: OS Independent
Requires-Python: >=3.6
License-File: LICENSE
Requires-Dist: beautifulsoup4
Requires-Dist: boto3
Requires-Dist: botocore
Requires-Dist: m3u8
Requires-Dist: pandas
Requires-Dist: ffmpeg-python
Requires-Dist: pytz
Requires-Dist: requests
Requires-Dist: tqdm
